README.md
setup.py
src/asr_business/__init__.py
src/asr_business/_version.py
src/asr_business/asr.py
src/asr_business/chinese2digits.py
src/asr_business/inke_asr.py
src/asr_business/models.py
src/asr_business/utils.py
src/asr_business/vad.py
src/asr_business/voiceprint.py
src/asr_business.egg-info/PKG-INFO
src/asr_business.egg-info/SOURCES.txt
src/asr_business.egg-info/dependency_links.txt
src/asr_business.egg-info/requires.txt
src/asr_business.egg-info/top_level.txt