Metadata-Version: 2.4
Name: asr_business
Version: 0.4.1
Home-page: https://github.com/Tonywu2018/asr_business
Author: wuwenxiao
Author-email: wuwenxiao@inke.cn
License: MIT Licence
Platform: any
Classifier: Programming Language :: Python :: 3
Classifier: License :: OSI Approved :: MIT License
Classifier: Operating System :: OS Independent
Requires-Python: >=3.8
Requires-Dist: torch==2.4.0
Requires-Dist: funasr
Requires-Dist: funasr-onnx
Requires-Dist: noisereduce
Requires-Dist: pydub
Requires-Dist: soundfile
Dynamic: author
Dynamic: author-email
Dynamic: classifier
Dynamic: description
Dynamic: description-content-type
Dynamic: home-page
Dynamic: license
Dynamic: platform
Dynamic: requires-dist
Dynamic: requires-python
